{
  "danceability": 0.638,
  "energy": 0.311,
  "key": 5,
  "loudness": -15.893,
  "mode": 0,
  "speechiness": 0.0368,
  "acousticness": 0.305,
  "instrumentalness": 0.00000317,
  "liveness": 0.0721,
  "valence": 0.754,
  "tempo": 83.418,
  "type": "audio_features",
  "id": "068DP8v87ywqLfdzgWRO3v",
  "uri": "spotify:track:068DP8v87ywqLfdzgWRO3v",
  "track_href": "https://api.spotify.com/v1/tracks/068DP8v87ywqLfdzgWRO3v",
  "analysis_url": "https://api.spotify.com/v1/audio-analysis/068DP8v87ywqLfdzgWRO3v",
  "duration_ms": 210071,
  "time_signature": 4
}