{
  "danceability": 0.682,
  "energy": 0.595,
  "key": 9,
  "loudness": -7.967,
  "mode": 0,
  "speechiness": 0.0431,
  "acousticness": 0.494,
  "instrumentalness": 0.109,
  "liveness": 0.27,
  "valence": 0.4,
  "tempo": 119.997,
  "type": "audio_features",
  "id": "0aOT5OQeNPyZzGwwudbaYs",
  "uri": "spotify:track:0aOT5OQeNPyZzGwwudbaYs",
  "track_href": "https://api.spotify.com/v1/tracks/0aOT5OQeNPyZzGwwudbaYs",
  "analysis_url": "https://api.spotify.com/v1/audio-analysis/0aOT5OQeNPyZzGwwudbaYs",
  "duration_ms": 247862,
  "time_signature": 4
}