{
  "danceability": 0.362,
  "energy": 0.715,
  "key": 9,
  "loudness": -7.115,
  "mode": 0,
  "speechiness": 0.0352,
  "acousticness": 0.000197,
  "instrumentalness": 0.925,
  "liveness": 0.061,
  "valence": 0.188,
  "tempo": 102.999,
  "type": "audio_features",
  "id": "0h74NmMIBUP5Q3iJf73VqC",
  "uri": "spotify:track:0h74NmMIBUP5Q3iJf73VqC",
  "track_href": "https://api.spotify.com/v1/tracks/0h74NmMIBUP5Q3iJf73VqC",
  "analysis_url": "https://api.spotify.com/v1/audio-analysis/0h74NmMIBUP5Q3iJf73VqC",
  "duration_ms": 59133,
  "time_signature": 4
}