{
  "danceability": 0.396,
  "energy": 0.813,
  "key": 2,
  "loudness": -3.911,
  "mode": 0,
  "speechiness": 0.0348,
  "acousticness": 0.0114,
  "instrumentalness": 0.00000394,
  "liveness": 0.324,
  "valence": 0.422,
  "tempo": 85.019,
  "type": "audio_features",
  "id": "0s28qR4TvOmbHZwKzkeeRj",
  "uri": "spotify:track:0s28qR4TvOmbHZwKzkeeRj",
  "track_href": "https://api.spotify.com/v1/tracks/0s28qR4TvOmbHZwKzkeeRj",
  "analysis_url": "https://api.spotify.com/v1/audio-analysis/0s28qR4TvOmbHZwKzkeeRj",
  "duration_ms": 224973,
  "time_signature": 4
}