{
  "danceability": 0.593,
  "energy": 0.537,
  "key": 2,
  "loudness": -6.672,
  "mode": 1,
  "speechiness": 0.0674,
  "acousticness": 0.835,
  "instrumentalness": 0.00000188,
  "liveness": 0.0689,
  "valence": 0.587,
  "tempo": 92.734,
  "type": "audio_features",
  "id": "0wxF2Ia8RldcEHSlEope7i",
  "uri": "spotify:track:0wxF2Ia8RldcEHSlEope7i",
  "track_href": "https://api.spotify.com/v1/tracks/0wxF2Ia8RldcEHSlEope7i",
  "analysis_url": "https://api.spotify.com/v1/audio-analysis/0wxF2Ia8RldcEHSlEope7i",
  "duration_ms": 212493,
  "time_signature": 4
}