{
  "danceability": 0.421,
  "energy": 0.285,
  "key": 2,
  "loudness": -9.43,
  "mode": 0,
  "speechiness": 0.0293,
  "acousticness": 0.829,
  "instrumentalness": 0.00000155,
  "liveness": 0.233,
  "valence": 0.402,
  "tempo": 85.861,
  "type": "audio_features",
  "id": "0zGLlXbHlrAyBN1x6sY0rb",
  "uri": "spotify:track:0zGLlXbHlrAyBN1x6sY0rb",
  "track_href": "https://api.spotify.com/v1/tracks/0zGLlXbHlrAyBN1x6sY0rb",
  "analysis_url": "https://api.spotify.com/v1/audio-analysis/0zGLlXbHlrAyBN1x6sY0rb",
  "duration_ms": 196133,
  "time_signature": 4
}