{
  "danceability": 0.217,
  "energy": 0.0408,
  "key": 9,
  "loudness": -26.146,
  "mode": 0,
  "speechiness": 0.0379,
  "acousticness": 0.994,
  "instrumentalness": 0.912,
  "liveness": 0.0553,
  "valence": 0.0614,
  "tempo": 159.179,
  "type": "audio_features",
  "id": "11kFCPT3e5GGpDQhX6d4sD",
  "uri": "spotify:track:11kFCPT3e5GGpDQhX6d4sD",
  "track_href": "https://api.spotify.com/v1/tracks/11kFCPT3e5GGpDQhX6d4sD",
  "analysis_url": "https://api.spotify.com/v1/audio-analysis/11kFCPT3e5GGpDQhX6d4sD",
  "duration_ms": 260973,
  "time_signature": 3
}