{
  "danceability": 0.0699,
  "energy": 0.171,
  "key": 4,
  "loudness": -16.707,
  "mode": 1,
  "speechiness": 0.0387,
  "acousticness": 0.916,
  "instrumentalness": 0.84,
  "liveness": 0.161,
  "valence": 0.0459,
  "tempo": 75.508,
  "type": "audio_features",
  "id": "1MElAbKpw9DAO1nANvXgkn",
  "uri": "spotify:track:1MElAbKpw9DAO1nANvXgkn",
  "track_href": "https://api.spotify.com/v1/tracks/1MElAbKpw9DAO1nANvXgkn",
  "analysis_url": "https://api.spotify.com/v1/audio-analysis/1MElAbKpw9DAO1nANvXgkn",
  "duration_ms": 274913,
  "time_signature": 5
}