{
  "danceability": 0.114,
  "energy": 0.0711,
  "key": 2,
  "loudness": -18.822,
  "mode": 0,
  "speechiness": 0.0357,
  "acousticness": 0.942,
  "instrumentalness": 0.938,
  "liveness": 0.139,
  "valence": 0.0738,
  "tempo": 93.658,
  "type": "audio_features",
  "id": "20yTdgLODTuVJD6ZcBoodj",
  "uri": "spotify:track:20yTdgLODTuVJD6ZcBoodj",
  "track_href": "https://api.spotify.com/v1/tracks/20yTdgLODTuVJD6ZcBoodj",
  "analysis_url": "https://api.spotify.com/v1/audio-analysis/20yTdgLODTuVJD6ZcBoodj",
  "duration_ms": 306068,
  "time_signature": 4
}