{
  "danceability": 0.512,
  "energy": 0.805,
  "key": 7,
  "loudness": -5.441,
  "mode": 0,
  "speechiness": 0.0741,
  "acousticness": 0.000448,
  "instrumentalness": 0.0000769,
  "liveness": 0.279,
  "valence": 0.372,
  "tempo": 131.978,
  "type": "audio_features",
  "id": "3axBlc5ZziFkq8jrN3cuWx",
  "uri": "spotify:track:3axBlc5ZziFkq8jrN3cuWx",
  "track_href": "https://api.spotify.com/v1/tracks/3axBlc5ZziFkq8jrN3cuWx",
  "analysis_url": "https://api.spotify.com/v1/audio-analysis/3axBlc5ZziFkq8jrN3cuWx",
  "duration_ms": 239240,
  "time_signature": 4
}