{
  "danceability": 0.705,
  "energy": 0.56,
  "key": 0,
  "loudness": -7.512,
  "mode": 0,
  "speechiness": 0.0303,
  "acousticness": 0.354,
  "instrumentalness": 0.00154,
  "liveness": 0.08,
  "valence": 0.618,
  "tempo": 122.489,
  "type": "audio_features",
  "id": "4ml6OwAuZ3fTaLRtCqr4fu",
  "uri": "spotify:track:4ml6OwAuZ3fTaLRtCqr4fu",
  "track_href": "https://api.spotify.com/v1/tracks/4ml6OwAuZ3fTaLRtCqr4fu",
  "analysis_url": "https://api.spotify.com/v1/audio-analysis/4ml6OwAuZ3fTaLRtCqr4fu",
  "duration_ms": 244973,
  "time_signature": 4
}