{
  "danceability": 0.103,
  "energy": 0.384,
  "key": 0,
  "loudness": -16.401,
  "mode": 0,
  "speechiness": 0.0556,
  "acousticness": 0.549,
  "instrumentalness": 0.897,
  "liveness": 0.111,
  "valence": 0.0747,
  "tempo": 79.262,
  "type": "audio_features",
  "id": "4u4VElxO7JM4IR4jR4TL1s",
  "uri": "spotify:track:4u4VElxO7JM4IR4jR4TL1s",
  "track_href": "https://api.spotify.com/v1/tracks/4u4VElxO7JM4IR4jR4TL1s",
  "analysis_url": "https://api.spotify.com/v1/audio-analysis/4u4VElxO7JM4IR4jR4TL1s",
  "duration_ms": 326773,
  "time_signature": 4
}