{
  "danceability": 0.462,
  "energy": 0.91,
  "key": 1,
  "loudness": -7.198,
  "mode": 1,
  "speechiness": 0.0359,
  "acousticness": 0.0000858,
  "instrumentalness": 0.0469,
  "liveness": 0.0863,
  "valence": 0.616,
  "tempo": 155.69,
  "type": "audio_features",
  "id": "5he7AYCR3MGloRnuWEMroT",
  "uri": "spotify:track:5he7AYCR3MGloRnuWEMroT",
  "track_href": "https://api.spotify.com/v1/tracks/5he7AYCR3MGloRnuWEMroT",
  "analysis_url": "https://api.spotify.com/v1/audio-analysis/5he7AYCR3MGloRnuWEMroT",
  "duration_ms": 214907,
  "time_signature": 4
}