{
  "danceability": 0.575,
  "energy": 0.789,
  "key": 7,
  "loudness": -8.503,
  "mode": 0,
  "speechiness": 0.0324,
  "acousticness": 0.0296,
  "instrumentalness": 0.00532,
  "liveness": 0.123,
  "valence": 0.291,
  "tempo": 129.86,
  "type": "audio_features",
  "id": "5oQrjFYt6Vqv5oi9KB1DPU",
  "uri": "spotify:track:5oQrjFYt6Vqv5oi9KB1DPU",
  "track_href": "https://api.spotify.com/v1/tracks/5oQrjFYt6Vqv5oi9KB1DPU",
  "analysis_url": "https://api.spotify.com/v1/audio-analysis/5oQrjFYt6Vqv5oi9KB1DPU",
  "duration_ms": 251667,
  "time_signature": 4
}