{
  "danceability": 0.617,
  "energy": 0.843,
  "key": 4,
  "loudness": -8.691,
  "mode": 0,
  "speechiness": 0.0361,
  "acousticness": 0.0559,
  "instrumentalness": 0.878,
  "liveness": 0.0948,
  "valence": 0.9,
  "tempo": 93.004,
  "type": "audio_features",
  "id": "78klvm18iP3pRQmaDRyR1E",
  "uri": "spotify:track:78klvm18iP3pRQmaDRyR1E",
  "track_href": "https://api.spotify.com/v1/tracks/78klvm18iP3pRQmaDRyR1E",
  "analysis_url": "https://api.spotify.com/v1/audio-analysis/78klvm18iP3pRQmaDRyR1E",
  "duration_ms": 303574,
  "time_signature": 4
}