{
  "album": {
    "album_type": "album",
    "artists": [
      {
        "external_urls": {
          "spotify": "https://open.spotify.com/artist/71wy5iisVKXLZgoPxdFi8A"
        },
        "href": "https://api.spotify.com/v1/artists/71wy5iisVKXLZgoPxdFi8A",
        "id": "71wy5iisVKXLZgoPxdFi8A",
        "name": "Les Misérables Cast",
        "type": "artist",
        "uri": "spotify:artist:71wy5iisVKXLZgoPxdFi8A"
      }
    ],
    "available_markets": [
      "AD",
      "AE",
      "AG",
      "AL",
      "AM",
      "AO",
      "AR",
      "AT",
      "AU",
      "AZ",
      "BA",
      "BB",
      "BE",
      "BF",
      "BG",
      "BH",
      "BI",
      "BJ",
      "BN",
      "BO",
      "BR",
      "BS",
      "BT",
      "BW",
      "BY",
      "BZ",
      "CD",
      "CG",
      "CH",
      "CI",
      "CL",
      "CM",
      "CO",
      "CR",
      "CV",
      "CY",
      "CZ",
      "DE",
      "DJ",
      "DK",
      "DM",
      "DO",
      "DZ",
      "EC",
      "EE",
      "EG",
      "ES",
      "FI",
      "FJ",
      "FM",
      "FR",
      "GA",
      "GB",
      "GD",
      "GH",
      "GM",
      "GN",
      "GQ",
      "GR",
      "GT",
      "GW",
      "GY",
      "HK",
      "HN",
      "HR",
      "HU",
      "ID",
      "IE",
      "IL",
      "IN",
      "IQ",
      "IS",
      "IT",
      "JM",
      "JO",
      "KE",
      "KG",
      "KH",
      "KM",
      "KN",
      "KR",
      "KW",
      "KZ",
      "LA",
      "LB",
      "LC",
      "LI",
      "LK",
      "LR",
      "LS",
      "LT",
      "LU",
      "LV",
      "MC",
      "MD",
      "ME",
      "MG",
      "MK",
      "ML",
      "MN",
      "MO",
      "MR",
      "MT",
      "MU",
      "MV",
      "MW",
      "MY",
      "MZ",
      "NA",
      "NE",
      "NG",
      "NI",
      "NL",
      "NO",
      "NP",
      "NZ",
      "OM",
      "PA",
      "PE",
      "PG",
      "PH",
      "PK",
      "PL",
      "PT",
      "PW",
      "PY",
      "QA",
      "RO",
      "RS",
      "RW",
      "SA",
      "SB",
      "SC",
      "SE",
      "SG",
      "SI",
      "SK",
      "SL",
      "SN",
      "SR",
      "ST",
      "SV",
      "SZ",
      "TD",
      "TG",
      "TH",
      "TJ",
      "TL",
      "TN",
      "TR",
      "TT",
      "TW",
      "TZ",
      "UA",
      "UG",
      "UY",
      "UZ",
      "VC",
      "VE",
      "VN",
      "XK",
      "ZA",
      "ZM",
      "ZW"
    ],
    "external_urls": {
      "spotify": "https://open.spotify.com/album/20exLke5P8o4D1Bj4iRcPf"
    },
    "href": "https://api.spotify.com/v1/albums/20exLke5P8o4D1Bj4iRcPf",
    "id": "20exLke5P8o4D1Bj4iRcPf",
    "images": [
      {
        "height": 640,
        "url": "https://i.scdn.co/image/ab67616d0000b273170e79548d280867ef12742b",
        "width": 640
      },
      {
        "height": 300,
        "url": "https://i.scdn.co/image/ab67616d00001e02170e79548d280867ef12742b",
        "width": 300
      },
      {
        "height": 64,
        "url": "https://i.scdn.co/image/ab67616d00004851170e79548d280867ef12742b",
        "width": 64
      }
    ],
    "name": "Les Misérables: The Motion Picture Soundtrack Deluxe (Deluxe Edition)",
    "release_date": "2013-01-01",
    "release_date_precision": "day",
    "total_tracks": 42,
    "type": "album",
    "uri": "spotify:album:20exLke5P8o4D1Bj4iRcPf"
  },
  "artists": [
    {
      "external_urls": {
        "spotify": "https://open.spotify.com/artist/68h2f0WXn4zEctSgNYozXx"
      },
      "href": "https://api.spotify.com/v1/artists/68h2f0WXn4zEctSgNYozXx",
      "id": "68h2f0WXn4zEctSgNYozXx",
      "name": "Aaron Tveit",
      "type": "artist",
      "uri": "spotify:artist:68h2f0WXn4zEctSgNYozXx"
    },
    {
      "external_urls": {
        "spotify": "https://open.spotify.com/artist/4EJP6Qhk6l18LumCcpEfLw"
      },
      "href": "https://api.spotify.com/v1/artists/4EJP6Qhk6l18LumCcpEfLw",
      "id": "4EJP6Qhk6l18LumCcpEfLw",
      "name": "Eddie Redmayne",
      "type": "artist",
      "uri": "spotify:artist:4EJP6Qhk6l18LumCcpEfLw"
    },
    {
      "external_urls": {
        "spotify": "https://open.spotify.com/artist/7oaoEBdRqHXfoiGYa55Atp"
      },
      "href": "https://api.spotify.com/v1/artists/7oaoEBdRqHXfoiGYa55Atp",
      "id": "7oaoEBdRqHXfoiGYa55Atp",
      "name": "Students",
      "type": "artist",
      "uri": "spotify:artist:7oaoEBdRqHXfoiGYa55Atp"
    },
    {
      "external_urls": {
        "spotify": "https://open.spotify.com/artist/71wy5iisVKXLZgoPxdFi8A"
      },
      "href": "https://api.spotify.com/v1/artists/71wy5iisVKXLZgoPxdFi8A",
      "id": "71wy5iisVKXLZgoPxdFi8A",
      "name": "Les Misérables Cast",
      "type": "artist",
      "uri": "spotify:artist:71wy5iisVKXLZgoPxdFi8A"
    }
  ],
  "available_markets": [
    "AD",
    "AE",
    "AG",
    "AL",
    "AM",
    "AO",
    "AR",
    "AT",
    "AU",
    "AZ",
    "BA",
    "BB",
    "BE",
    "BF",
    "BG",
    "BH",
    "BI",
    "BJ",
    "BN",
    "BO",
    "BR",
    "BS",
    "BT",
    "BW",
    "BY",
    "BZ",
    "CD",
    "CG",
    "CH",
    "CI",
    "CL",
    "CM",
    "CO",
    "CR",
    "CV",
    "CY",
    "CZ",
    "DE",
    "DJ",
    "DK",
    "DM",
    "DO",
    "DZ",
    "EC",
    "EE",
    "EG",
    "ES",
    "FI",
    "FJ",
    "FM",
    "FR",
    "GA",
    "GB",
    "GD",
    "GH",
    "GM",
    "GN",
    "GQ",
    "GR",
    "GT",
    "GW",
    "GY",
    "HK",
    "HN",
    "HR",
    "HU",
    "ID",
    "IE",
    "IL",
    "IN",
    "IQ",
    "IS",
    "IT",
    "JM",
    "JO",
    "KE",
    "KG",
    "KH",
    "KM",
    "KN",
    "KR",
    "KW",
    "KZ",
    "LA",
    "LB",
    "LC",
    "LI",
    "LK",
    "LR",
    "LS",
    "LT",
    "LU",
    "LV",
    "MC",
    "MD",
    "ME",
    "MG",
    "MK",
    "ML",
    "MN",
    "MO",
    "MR",
    "MT",
    "MU",
    "MV",
    "MW",
    "MY",
    "MZ",
    "NA",
    "NE",
    "NG",
    "NI",
    "NL",
    "NO",
    "NP",
    "NZ",
    "OM",
    "PA",
    "PE",
    "PG",
    "PH",
    "PK",
    "PL",
    "PT",
    "PW",
    "PY",
    "QA",
    "RO",
    "RS",
    "RW",
    "SA",
    "SB",
    "SC",
    "SE",
    "SG",
    "SI",
    "SK",
    "SL",
    "SN",
    "SR",
    "ST",
    "SV",
    "SZ",
    "TD",
    "TG",
    "TH",
    "TJ",
    "TL",
    "TN",
    "TR",
    "TT",
    "TW",
    "TZ",
    "UA",
    "UG",
    "UY",
    "UZ",
    "VC",
    "VE",
    "VN",
    "XK",
    "ZA",
    "ZM",
    "ZW"
  ],
  "disc_number": 2,
  "duration_ms": 123160,
  "explicit": false,
  "external_ids": {
    "isrc": "GBUM71301285"
  },
  "external_urls": {
    "spotify": "https://open.spotify.com/track/03m03OVQGPuzt8Rw2r0a7t"
  },
  "href": "https://api.spotify.com/v1/tracks/03m03OVQGPuzt8Rw2r0a7t",
  "id": "03m03OVQGPuzt8Rw2r0a7t",
  "is_local": false,
  "name": "Do You Hear The People Sing?",
  "popularity": 53,
  "preview_url": null,
  "track_number": 1,
  "type": "track",
  "uri": "spotify:track:03m03OVQGPuzt8Rw2r0a7t"
}